[
  {
    "discovered_at": "2026-06-11T07:31:51+00:00",
    "platform": "polymarket",
    "source": "gamma_events",
    "event_id": "30615",
    "event_slug": "world-cup-winner",
    "event_title": "World Cup Winner ",
    "market_id": "558934",
    "market_slug": "will-spain-win-the-2026-fifa-world-cup-963",
    "question": "Will Spain win the 2026 FIFA World Cup?",
    "event_type": "champion_or_outright",
    "active": true,
    "closed": false,
    "accepting_orders": "True",
    "end_date": "2026-07-20T00:00:00Z",
    "volume": 37353509.89236248,
    "volume_24hr": 2506960.056268008,
    "liquidity": 1227806.9725,
    "open_interest": 29394581.941327006,
    "best_bid": "0.169",
    "best_ask": "0.17",
    "last_trade_price": "0.17",
    "outcome_prices": "[\"0.1695\", \"0.8305\"]",
    "outcomes": "[\"Yes\", \"No\"]",
    "url": "https://polymarket.com/event/world-cup-winner",
    "matched_keywords": "2026;fifa;spain;world cup",
    "notes": ""
  },
  {
    "discovered_at": "2026-06-11T07:31:51+00:00",
    "platform": "polymarket",
    "source": "gamma_events",
    "event_id": "30615",
    "event_slug": "world-cup-winner",
    "event_title": "World Cup Winner ",
    "market_id": "558957",
    "market_slug": "will-new-zealand-win-the-2026-fifa-world-cup-635",
    "question": "Will New Zealand win the 2026 FIFA World Cup?",
    "event_type": "champion_or_outright",
    "active": true,
    "closed": false,
    "accepting_orders": "True",
    "end_date": "2026-07-20T00:00:00Z",
    "volume": 45479806.612645194,
    "volume_24hr": 177885.0,
    "liquidity": 17175829.0302,
    "open_interest": 29394581.941327006,
    "best_bid": "",
    "best_ask": "0.001",
    "last_trade_price": "0.001",
    "outcome_prices": "[\"0.0005\", \"0.9995\"]",
    "outcomes": "[\"Yes\", \"No\"]",
    "url": "https://polymarket.com/event/world-cup-winner",
    "matched_keywords": "2026;fifa;new zealand;world cup",
    "notes": ""
  },
  {
    "discovered_at": "2026-06-11T07:31:51+00:00",
    "platform": "polymarket",
    "source": "gamma_events",
    "event_id": "30615",
    "event_slug": "world-cup-winner",
    "event_title": "World Cup Winner ",
    "market_id": "558974",
    "market_slug": "will-switzerland-win-the-2026-fifa-world-cup",
    "question": "Will Switzerland win the 2026 FIFA World Cup?",
    "event_type": "champion_or_outright",
    "active": true,
    "closed": false,
    "accepting_orders": "True",
    "end_date": "2026-07-20T00:00:00Z",
    "volume": 38911214.64049669,
    "volume_24hr": 3116450.121577999,
    "liquidity": 1943193.97911,
    "open_interest": 29394581.941327006,
    "best_bid": "0.012",
    "best_ask": "0.013",
    "last_trade_price": "0.013",
    "outcome_prices": "[\"0.0125\", \"0.9875\"]",
    "outcomes": "[\"Yes\", \"No\"]",
    "url": "https://polymarket.com/event/world-cup-winner",
    "matched_keywords": "2026;fifa;switzerland;world cup",
    "notes": ""
  },
  {
    "discovered_at": "2026-06-11T07:31:51+00:00",
    "platform": "polymarket",
    "source": "gamma_events",
    "event_id": "30615",
    "event_slug": "world-cup-winner",
    "event_title": "World Cup Winner ",
    "market_id": "558935",
    "market_slug": "will-england-win-the-2026-fifa-world-cup-937",
    "question": "Will England win the 2026 FIFA World Cup?",
    "event_type": "champion_or_outright",
    "active": true,
    "closed": false,
    "accepting_orders": "True",
    "end_date": "2026-07-20T00:00:00Z",
    "volume": 32359256.545917388,
    "volume_24hr": 2149340.247752992,
    "liquidity": 1620452.53234,
    "open_interest": 29394581.941327006,
    "best_bid": "0.108",
    "best_ask": "0.109",
    "last_trade_price": "0.108",
    "outcome_prices": "[\"0.1085\", \"0.8915\"]",
    "outcomes": "[\"Yes\", \"No\"]",
    "url": "https://polymarket.com/event/world-cup-winner",
    "matched_keywords": "2026;england;fifa;world cup",
    "notes": ""
  },
  {
    "discovered_at": "2026-06-11T07:31:51+00:00",
    "platform": "polymarket",
    "source": "gamma_events",
    "event_id": "30615",
    "event_slug": "world-cup-winner",
    "event_title": "World Cup Winner ",
    "market_id": "558992",
    "market_slug": "will-team-am-win-the-2026-fifa-world-cup",
    "question": "Will Team AM win the 2026 FIFA World Cup?",
    "event_type": "champion_or_outright",
    "active": false,
    "closed": false,
    "accepting_orders": "True",
    "end_date": "2026-07-20T00:00:00Z",
    "volume": 0.0,
    "volume_24hr": 0.0,
    "liquidity": 0.0,
    "open_interest": 29394581.941327006,
    "best_bid": "0",
    "best_ask": "1",
    "last_trade_price": "0",
    "outcome_prices": "",
    "outcomes": "[\"Yes\", \"No\"]",
    "url": "https://polymarket.com/event/world-cup-winner",
    "matched_keywords": "2026;fifa;world cup",
    "notes": ""
  },
  {
    "discovered_at": "2026-06-11T07:31:51+00:00",
    "platform": "polymarket",
    "source": "gamma_events",
    "event_id": "30615",
    "event_slug": "world-cup-winner",
    "event_title": "World Cup Winner ",
    "market_id": "558936",
    "market_slug": "will-france-win-the-2026-fifa-world-cup-924",
    "question": "Will France win the 2026 FIFA World Cup?",
    "event_type": "champion_or_outright",
    "active": true,
    "closed": false,
    "accepting_orders": "True",
    "end_date": "2026-07-20T00:00:00Z",
    "volume": 43867038.44631219,
    "volume_24hr": 1594700.9996900002,
    "liquidity": 1354697.74813,
    "open_interest": 29394581.941327006,
    "best_bid": "0.16",
    "best_ask": "0.161",
    "last_trade_price": "0.161",
    "outcome_prices": "[\"0.1605\", \"0.8395\"]",
    "outcomes": "[\"Yes\", \"No\"]",
    "url": "https://polymarket.com/event/world-cup-winner",
    "matched_keywords": "2026;fifa;france;world cup",
    "notes": ""
  },
  {
    "discovered_at": "2026-06-11T07:31:51+00:00",
    "platform": "polymarket",
    "source": "gamma_events",
    "event_id": "30615",
    "event_slug": "world-cup-winner",
    "event_title": "World Cup Winner ",
    "market_id": "558961",
    "market_slug": "will-south-korea-win-the-2026-fifa-world-cup-485",
    "question": "Will South Korea win the 2026 FIFA World Cup?",
    "event_type": "champion_or_outright",
    "active": true,
    "closed": false,
    "accepting_orders": "True",
    "end_date": "2026-07-20T00:00:00Z",
    "volume": 48244001.886560805,
    "volume_24hr": 2634420.589467002,
    "liquidity": 4059979.73821,
    "open_interest": 29394581.941327006,
    "best_bid": "0.002",
    "best_ask": "0.003",
    "last_trade_price": "0.003",
    "outcome_prices": "[\"0.0025\", \"0.9975\"]",
    "outcomes": "[\"Yes\", \"No\"]",
    "url": "https://polymarket.com/event/world-cup-winner",
    "matched_keywords": "2026;fifa;korea;world cup",
    "notes": ""
  },
  {
    "discovered_at": "2026-06-11T07:31:51+00:00",
    "platform": "polymarket",
    "source": "gamma_events",
    "event_id": "30615",
    "event_slug": "world-cup-winner",
    "event_title": "World Cup Winner ",
    "market_id": "558977",
    "market_slug": "will-haiti-win-the-2026-fifa-world-cup",
    "question": "Will Haiti win the 2026 FIFA World Cup?",
    "event_type": "champion_or_outright",
    "active": true,
    "closed": false,
    "accepting_orders": "True",
    "end_date": "2026-07-20T00:00:00Z",
    "volume": 32022190.571820088,
    "volume_24hr": 125280.0,
    "liquidity": 16913731.50745,
    "open_interest": 29394581.941327006,
    "best_bid": "",
    "best_ask": "0.001",
    "last_trade_price": "0.001",
    "outcome_prices": "[\"0.0005\", \"0.9995\"]",
    "outcomes": "[\"Yes\", \"No\"]",
    "url": "https://polymarket.com/event/world-cup-winner",
    "matched_keywords": "2026;fifa;haiti;world cup",
    "notes": ""
  },
  {
    "discovered_at": "2026-06-11T07:31:51+00:00",
    "platform": "polymarket",
    "source": "gamma_events",
    "event_id": "30615",
    "event_slug": "world-cup-winner",
    "event_title": "World Cup Winner ",
    "market_id": "558937",
    "market_slug": "will-brazil-win-the-2026-fifa-world-cup-183",
    "question": "Will Brazil win the 2026 FIFA World Cup?",
    "event_type": "champion_or_outright",
    "active": true,
    "closed": false,
    "accepting_orders": "True",
    "end_date": "2026-07-20T00:00:00Z",
    "volume": 33905401.36231603,
    "volume_24hr": 2123375.600939994,
    "liquidity": 1837953.77661,
    "open_interest": 29394581.941327006,
    "best_bid": "0.084",
    "best_ask": "0.085",
    "last_trade_price": "0.085",
    "outcome_prices": "[\"0.0845\", \"0.9155\"]",
    "outcomes": "[\"Yes\", \"No\"]",
    "url": "https://polymarket.com/event/world-cup-winner",
    "matched_keywords": "2026;brazil;fifa;world cup",
    "notes": ""
  },
  {
    "discovered_at": "2026-06-11T07:31:51+00:00",
    "platform": "polymarket",
    "source": "gamma_events",
    "event_id": "30615",
    "event_slug": "world-cup-winner",
    "event_title": "World Cup Winner ",
    "market_id": "558962",
    "market_slug": "will-jordan-win-the-2026-fifa-world-cup-233",
    "question": "Will Jordan win the 2026 FIFA World Cup?",
    "event_type": "champion_or_outright",
    "active": true,
    "closed": false,
    "accepting_orders": "True",
    "end_date": "2026-07-20T00:00:00Z",
    "volume": 31607892.441882774,
    "volume_24hr": 242820.0,
    "liquidity": 17086458.71601,
    "open_interest": 29394581.941327006,
    "best_bid": "",
    "best_ask": "0.001",
    "last_trade_price": "0.001",
    "outcome_prices": "[\"0.0005\", \"0.9995\"]",
    "outcomes": "[\"Yes\", \"No\"]",
    "url": "https://polymarket.com/event/world-cup-winner",
    "matched_keywords": "2026;fifa;jordan;world cup",
    "notes": ""
  },
  {
    "discovered_at": "2026-06-11T07:31:51+00:00",
    "platform": "polymarket",
    "source": "gamma_events",
    "event_id": "30615",
    "event_slug": "world-cup-winner",
    "event_title": "World Cup Winner ",
    "market_id": "558978",
    "market_slug": "will-curaao-win-the-2026-fifa-world-cup",
    "question": "Will Curaçao win the 2026 FIFA World Cup?",
    "event_type": "champion_or_outright",
    "active": true,
    "closed": false,
    "accepting_orders": "True",
    "end_date": "2026-07-20T00:00:00Z",
    "volume": 41628753.67691622,
    "volume_24hr": 193550.0,
    "liquidity": 16803841.28083,
    "open_interest": 29394581.941327006,
    "best_bid": "",
    "best_ask": "0.001",
    "last_trade_price": "0.001",
    "outcome_prices": "[\"0.0005\", \"0.9995\"]",
    "outcomes": "[\"Yes\", \"No\"]",
    "url": "https://polymarket.com/event/world-cup-winner",
    "matched_keywords": "2026;fifa;world cup",
    "notes": ""
  },
  {
    "discovered_at": "2026-06-11T07:31:51+00:00",
    "platform": "polymarket",
    "source": "gamma_events",
    "event_id": "30615",
    "event_slug": "world-cup-winner",
    "event_title": "World Cup Winner ",
    "market_id": "558938",
    "market_slug": "will-argentina-win-the-2026-fifa-world-cup-245",
    "question": "Will Argentina win the 2026 FIFA World Cup?",
    "event_type": "champion_or_outright",
    "active": true,
    "closed": false,
    "accepting_orders": "True",
    "end_date": "2026-07-20T00:00:00Z",
    "volume": 34689224.75984702,
    "volume_24hr": 2831272.4526159973,
    "liquidity": 1022435.63168,
    "open_interest": 29394581.941327006,
    "best_bid": "0.093",
    "best_ask": "0.094",
    "last_trade_price": "0.093",
    "outcome_prices": "[\"0.0935\", \"0.9065\"]",
    "outcomes": "[\"Yes\", \"No\"]",
    "url": "https://polymarket.com/event/world-cup-winner",
    "matched_keywords": "2026;argentina;fifa;world cup",
    "notes": ""
  },
  {
    "discovered_at": "2026-06-11T07:31:51+00:00",
    "platform": "polymarket",
    "source": "gamma_events",
    "event_id": "30615",
    "event_slug": "world-cup-winner",
    "event_title": "World Cup Winner ",
    "market_id": "558939",
    "market_slug": "will-germany-win-the-2026-fifa-world-cup-467",
    "question": "Will Germany win the 2026 FIFA World Cup?",
    "event_type": "champion_or_outright",
    "active": true,
    "closed": false,
    "accepting_orders": "True",
    "end_date": "2026-07-20T00:00:00Z",
    "volume": 35745854.2497525,
    "volume_24hr": 1874169.525511998,
    "liquidity": 2503087.45639,
    "open_interest": 29394581.941327006,
    "best_bid": "0.052",
    "best_ask": "0.053",
    "last_trade_price": "0.052",
    "outcome_prices": "[\"0.0525\", \"0.9475\"]",
    "outcomes": "[\"Yes\", \"No\"]",
    "url": "https://polymarket.com/event/world-cup-winner",
    "matched_keywords": "2026;fifa;germany;world cup",
    "notes": ""
  },
  {
    "discovered_at": "2026-06-11T07:31:51+00:00",
    "platform": "polymarket",
    "source": "gamma_events",
    "event_id": "30615",
    "event_slug": "world-cup-winner",
    "event_title": "World Cup Winner ",
    "market_id": "558947",
    "market_slug": "will-colombia-win-the-2026-fifa-world-cup-734",
    "question": "Will Colombia win the 2026 FIFA World Cup?",
    "event_type": "champion_or_outright",
    "active": true,
    "closed": false,
    "accepting_orders": "True",
    "end_date": "2026-07-20T00:00:00Z",
    "volume": 39617840.32483591,
    "volume_24hr": 2924112.1634880085,
    "liquidity": 4617738.96458,
    "open_interest": 29394581.941327006,
    "best_bid": "0.018",
    "best_ask": "0.019",
    "last_trade_price": "0.018",
    "outcome_prices": "[\"0.0185\", \"0.9815\"]",
    "outcomes": "[\"Yes\", \"No\"]",
    "url": "https://polymarket.com/event/world-cup-winner",
    "matched_keywords": "2026;colombia;fifa;world cup",
    "notes": ""
  },
  {
    "discovered_at": "2026-06-11T07:31:51+00:00",
    "platform": "polymarket",
    "source": "gamma_events",
    "event_id": "30615",
    "event_slug": "world-cup-winner",
    "event_title": "World Cup Winner ",
    "market_id": "558959",
    "market_slug": "will-iran-win-the-2026-fifa-world-cup-788",
    "question": "Will Iran win the 2026 FIFA World Cup?",
    "event_type": "champion_or_outright",
    "active": true,
    "closed": false,
    "accepting_orders": "True",
    "end_date": "2026-07-20T00:00:00Z",
    "volume": 44440305.74579001,
    "volume_24hr": 2581287.765000005,
    "liquidity": 10591010.27852,
    "open_interest": 29394581.941327006,
    "best_bid": "0.001",
    "best_ask": "0.002",
    "last_trade_price": "0.001",
    "outcome_prices": "[\"0.0015\", \"0.9985\"]",
    "outcomes": "[\"Yes\", \"No\"]",
    "url": "https://polymarket.com/event/world-cup-winner",
    "matched_keywords": "2026;fifa;iran;world cup",
    "notes": ""
  },
  {
    "discovered_at": "2026-06-11T07:31:51+00:00",
    "platform": "polymarket",
    "source": "gamma_events",
    "event_id": "30615",
    "event_slug": "world-cup-winner",
    "event_title": "World Cup Winner ",
    "market_id": "558940",
    "market_slug": "will-portugal-win-the-2026-fifa-world-cup-912",
    "question": "Will Portugal win the 2026 FIFA World Cup?",
    "event_type": "champion_or_outright",
    "active": true,
    "closed": false,
    "accepting_orders": "True",
    "end_date": "2026-07-20T00:00:00Z",
    "volume": 39083078.36141137,
    "volume_24hr": 2536328.4757589963,
    "liquidity": 474004.57437,
    "open_interest": 29394581.941327006,
    "best_bid": "0.109",
    "best_ask": "0.11",
    "last_trade_price": "0.109",
    "outcome_prices": "[\"0.1095\", \"0.8905\"]",
    "outcomes": "[\"Yes\", \"No\"]",
    "url": "https://polymarket.com/event/world-cup-winner",
    "matched_keywords": "2026;fifa;portugal;world cup",
    "notes": ""
  },
  {
    "discovered_at": "2026-06-11T07:31:51+00:00",
    "platform": "polymarket",
    "source": "gamma_events",
    "event_id": "30615",
    "event_slug": "world-cup-winner",
    "event_title": "World Cup Winner ",
    "market_id": "558967",
    "market_slug": "will-ghana-win-the-2026-fifa-world-cup",
    "question": "Will Ghana win the 2026 FIFA World Cup?",
    "event_type": "champion_or_outright",
    "active": true,
    "closed": false,
    "accepting_orders": "True",
    "end_date": "2026-07-20T00:00:00Z",
    "volume": 36799006.27844176,
    "volume_24hr": 1871704.432,
    "liquidity": 15425069.65472,
    "open_interest": 29394581.941327006,
    "best_bid": "0.001",
    "best_ask": "0.002",
    "last_trade_price": "0.001",
    "outcome_prices": "[\"0.0015\", \"0.9985\"]",
    "outcomes": "[\"Yes\", \"No\"]",
    "url": "https://polymarket.com/event/world-cup-winner",
    "matched_keywords": "2026;fifa;ghana;world cup",
    "notes": ""
  },
  {
    "discovered_at": "2026-06-11T07:31:51+00:00",
    "platform": "polymarket",
    "source": "gamma_events",
    "event_id": "30615",
    "event_slug": "world-cup-winner",
    "event_title": "World Cup Winner ",
    "market_id": "558941",
    "market_slug": "will-netherlands-win-the-2026-fifa-world-cup-739",
    "question": "Will Netherlands win the 2026 FIFA World Cup?",
    "event_type": "champion_or_outright",
    "active": true,
    "closed": false,
    "accepting_orders": "True",
    "end_date": "2026-07-20T00:00:00Z",
    "volume": 38393029.12293392,
    "volume_24hr": 3320307.629760017,
    "liquidity": 2270110.83974,
    "open_interest": 29394581.941327006,
    "best_bid": "0.04",
    "best_ask": "0.041",
    "last_trade_price": "0.041",
    "outcome_prices": "[\"0.0405\", \"0.9595\"]",
    "outcomes": "[\"Yes\", \"No\"]",
    "url": "https://polymarket.com/event/world-cup-winner",
    "matched_keywords": "2026;fifa;netherlands;world cup",
    "notes": ""
  },
  {
    "discovered_at": "2026-06-11T07:31:51+00:00",
    "platform": "polymarket",
    "source": "gamma_events",
    "event_id": "30615",
    "event_slug": "world-cup-winner",
    "event_title": "World Cup Winner ",
    "market_id": "558969",
    "market_slug": "will-algeria-win-the-2026-fifa-world-cup",
    "question": "Will Algeria win the 2026 FIFA World Cup?",
    "event_type": "champion_or_outright",
    "active": true,
    "closed": false,
    "accepting_orders": "True",
    "end_date": "2026-07-20T00:00:00Z",
    "volume": 44565216.914215535,
    "volume_24hr": 3960080.83,
    "liquidity": 8936193.55272,
    "open_interest": 29394581.941327006,
    "best_bid": "0.001",
    "best_ask": "0.002",
    "last_trade_price": "0.002",
    "outcome_prices": "[\"0.0015\", \"0.9985\"]",
    "outcomes": "[\"Yes\", \"No\"]",
    "url": "https://polymarket.com/event/world-cup-winner",
    "matched_keywords": "2026;algeria;fifa;world cup",
    "notes": ""
  },
  {
    "discovered_at": "2026-06-11T07:31:51+00:00",
    "platform": "polymarket",
    "source": "gamma_events",
    "event_id": "30615",
    "event_slug": "world-cup-winner",
    "event_title": "World Cup Winner ",
    "market_id": "558983",
    "market_slug": "will-bosnia-herzegovina-win-the-2026-fifa-world-cup",
    "question": "Will Bosnia-Herzegovina win the 2026 FIFA World Cup?",
    "event_type": "champion_or_outright",
    "active": true,
    "closed": false,
    "accepting_orders": "True",
    "end_date": "2026-07-20T00:00:00Z",
    "volume": 27786738.544717897,
    "volume_24hr": 3666405.637000005,
    "liquidity": 13683269.73922,
    "open_interest": 29394581.941327006,
    "best_bid": "0.001",
    "best_ask": "0.002",
    "last_trade_price": "0.002",
    "outcome_prices": "[\"0.0015\", \"0.9985\"]",
    "outcomes": "[\"Yes\", \"No\"]",
    "url": "https://polymarket.com/event/world-cup-winner",
    "matched_keywords": "2026;bosnia;fifa;world cup",
    "notes": ""
  },
  {
    "discovered_at": "2026-06-11T07:31:51+00:00",
    "platform": "polymarket",
    "source": "gamma_events",
    "event_id": "30615",
    "event_slug": "world-cup-winner",
    "event_title": "World Cup Winner ",
    "market_id": "558942",
    "market_slug": "will-italy-win-the-2026-fifa-world-cup-813",
    "question": "Will Italy win the 2026 FIFA World Cup?",
    "event_type": "champion_or_outright",
    "active": true,
    "closed": true,
    "accepting_orders": "False",
    "end_date": "2026-07-20T00:00:00Z",
    "volume": 8666273.297316846,
    "volume_24hr": 100849187.11207904,
    "liquidity": 384055178.75338,
    "open_interest": 29394581.941327006,
    "best_bid": "",
    "best_ask": "0.001",
    "last_trade_price": "0.001",
    "outcome_prices": "[\"0\", \"1\"]",
    "outcomes": "[\"Yes\", \"No\"]",
    "url": "https://polymarket.com/event/world-cup-winner",
    "matched_keywords": "2026;fifa;world cup",
    "notes": ""
  },
  {
    "discovered_at": "2026-06-11T07:31:51+00:00",
    "platform": "polymarket",
    "source": "gamma_events",
    "event_id": "30615",
    "event_slug": "world-cup-winner",
    "event_title": "World Cup Winner ",
    "market_id": "558943",
    "market_slug": "will-usa-win-the-2026-fifa-world-cup-467",
    "question": "Will USA win the 2026 FIFA World Cup?",
    "event_type": "champion_or_outright",
    "active": true,
    "closed": false,
    "accepting_orders": "True",
    "end_date": "2026-07-20T00:00:00Z",
    "volume": 56376219.782984145,
    "volume_24hr": 3574166.5842520064,
    "liquidity": 5371600.36157,
    "open_interest": 29394581.941327006,
    "best_bid": "0.011",
    "best_ask": "0.012",
    "last_trade_price": "0.012",
    "outcome_prices": "[\"0.0115\", \"0.9885\"]",
    "outcomes": "[\"Yes\", \"No\"]",
    "url": "https://polymarket.com/event/world-cup-winner",
    "matched_keywords": "2026;fifa;usa;world cup",
    "notes": ""
  },
  {
    "discovered_at": "2026-06-11T07:31:51+00:00",
    "platform": "polymarket",
    "source": "gamma_events",
    "event_id": "30615",
    "event_slug": "world-cup-winner",
    "event_title": "World Cup Winner ",
    "market_id": "558952",
    "market_slug": "will-canada-win-the-2026-fifa-world-cup-755",
    "question": "Will Canada win the 2026 FIFA World Cup?",
    "event_type": "champion_or_outright",
    "active": true,
    "closed": false,
    "accepting_orders": "True",
    "end_date": "2026-07-20T00:00:00Z",
    "volume": 43966851.47035802,
    "volume_24hr": 2077840.108964,
    "liquidity": 7527164.54735,
    "open_interest": 29394581.941327006,
    "best_bid": "0.003",
    "best_ask": "0.004",
    "last_trade_price": "0.004",
    "outcome_prices": "[\"0.0035\", \"0.9965\"]",
    "outcomes": "[\"Yes\", \"No\"]",
    "url": "https://polymarket.com/event/world-cup-winner",
    "matched_keywords": "2026;canada;fifa;world cup",
    "notes": ""
  },
  {
    "discovered_at": "2026-06-11T07:31:51+00:00",
    "platform": "polymarket",
    "source": "gamma_events",
    "event_id": "30615",
    "event_slug": "world-cup-winner",
    "event_title": "World Cup Winner ",
    "market_id": "558985",
    "market_slug": "will-turkiye-win-the-2026-fifa-world-cup",
    "question": "Will Turkiye win the 2026 FIFA World Cup?",
    "event_type": "champion_or_outright",
    "active": true,
    "closed": false,
    "accepting_orders": "True",
    "end_date": "2026-07-20T00:00:00Z",
    "volume": 36755608.901926234,
    "volume_24hr": 2016240.1026379997,
    "liquidity": 2513456.25422,
    "open_interest": 29394581.941327006,
    "best_bid": "0.012",
    "best_ask": "0.013",
    "last_trade_price": "0.013",
    "outcome_prices": "[\"0.0125\", \"0.9875\"]",
    "outcomes": "[\"Yes\", \"No\"]",
    "url": "https://polymarket.com/event/world-cup-winner",
    "matched_keywords": "2026;fifa;turkiye;world cup",
    "notes": ""
  },
  {
    "discovered_at": "2026-06-11T07:31:51+00:00",
    "platform": "polymarket",
    "source": "gamma_events",
    "event_id": "30615",
    "event_slug": "world-cup-winner",
    "event_title": "World Cup Winner ",
    "market_id": "558944",
    "market_slug": "will-uruguay-win-the-2026-fifa-world-cup-932",
    "question": "Will Uruguay win the 2026 FIFA World Cup?",
    "event_type": "champion_or_outright",
    "active": true,
    "closed": false,
    "accepting_orders": "True",
    "end_date": "2026-07-20T00:00:00Z",
    "volume": 39299581.108196,
    "volume_24hr": 2160109.009070003,
    "liquidity": 9435447.23003,
    "open_interest": 29394581.941327006,
    "best_bid": "0.01",
    "best_ask": "0.011",
    "last_trade_price": "0.01",
    "outcome_prices": "[\"0.0105\", \"0.9895\"]",
    "outcomes": "[\"Yes\", \"No\"]",
    "url": "https://polymarket.com/event/world-cup-winner",
    "matched_keywords": "2026;fifa;uruguay;world cup",
    "notes": ""
  },
  {
    "discovered_at": "2026-06-11T07:31:51+00:00",
    "platform": "polymarket",
    "source": "gamma_events",
    "event_id": "30615",
    "event_slug": "world-cup-winner",
    "event_title": "World Cup Winner ",
    "market_id": "558988",
    "market_slug": "will-team-ai-win-the-2026-fifa-world-cup",
    "question": "Will Team AI win the 2026 FIFA World Cup?",
    "event_type": "champion_or_outright",
    "active": false,
    "closed": false,
    "accepting_orders": "True",
    "end_date": "2026-07-20T00:00:00Z",
    "volume": 0.0,
    "volume_24hr": 0.0,
    "liquidity": 0.0,
    "open_interest": 29394581.941327006,
    "best_bid": "0",
    "best_ask": "1",
    "last_trade_price": "0",
    "outcome_prices": "",
    "outcomes": "[\"Yes\", \"No\"]",
    "url": "https://polymarket.com/event/world-cup-winner",
    "matched_keywords": "2026;fifa;world cup",
    "notes": ""
  },
  {
    "discovered_at": "2026-06-11T07:31:51+00:00",
    "platform": "polymarket",
    "source": "gamma_events",
    "event_id": "30615",
    "event_slug": "world-cup-winner",
    "event_title": "World Cup Winner ",
    "market_id": "558945",
    "market_slug": "will-mexico-win-the-2026-fifa-world-cup-529",
    "question": "Will Mexico win the 2026 FIFA World Cup?",
    "event_type": "champion_or_outright",
    "active": true,
    "closed": false,
    "accepting_orders": "True",
    "end_date": "2026-07-20T00:00:00Z",
    "volume": 44061348.82792281,
    "volume_24hr": 2226602.8972820006,
    "liquidity": 2312324.28578,
    "open_interest": 29394581.941327006,
    "best_bid": "0.013",
    "best_ask": "0.014",
    "last_trade_price": "0.014",
    "outcome_prices": "[\"0.0135\", \"0.9865\"]",
    "outcomes": "[\"Yes\", \"No\"]",
    "url": "https://polymarket.com/event/world-cup-winner",
    "matched_keywords": "2026;fifa;mexico;world cup",
    "notes": ""
  },
  {
    "discovered_at": "2026-06-11T07:31:51+00:00",
    "platform": "polymarket",
    "source": "gamma_events",
    "event_id": "30615",
    "event_slug": "world-cup-winner",
    "event_title": "World Cup Winner ",
    "market_id": "558956",
    "market_slug": "will-paraguay-win-the-2026-fifa-world-cup-967",
    "question": "Will Paraguay win the 2026 FIFA World Cup?",
    "event_type": "champion_or_outright",
    "active": true,
    "closed": false,
    "accepting_orders": "True",
    "end_date": "2026-07-20T00:00:00Z",
    "volume": 41925385.79183372,
    "volume_24hr": 6598255.979998001,
    "liquidity": 6049880.90302,
    "open_interest": 29394581.941327006,
    "best_bid": "0.001",
    "best_ask": "0.002",
    "last_trade_price": "0.002",
    "outcome_prices": "[\"0.0015\", \"0.9985\"]",
    "outcomes": "[\"Yes\", \"No\"]",
    "url": "https://polymarket.com/event/world-cup-winner",
    "matched_keywords": "2026;fifa;paraguay;world cup",
    "notes": ""
  },
  {
    "discovered_at": "2026-06-11T07:31:51+00:00",
    "platform": "polymarket",
    "source": "gamma_events",
    "event_id": "30615",
    "event_slug": "world-cup-winner",
    "event_title": "World Cup Winner ",
    "market_id": "558973",
    "market_slug": "will-scotland-win-the-2026-fifa-world-cup",
    "question": "Will Scotland win the 2026 FIFA World Cup?",
    "event_type": "champion_or_outright",
    "active": true,
    "closed": false,
    "accepting_orders": "True",
    "end_date": "2026-07-20T00:00:00Z",
    "volume": 42190879.93503155,
    "volume_24hr": 2962092.937484,
    "liquidity": 12704953.1601,
    "open_interest": 29394581.941327006,
    "best_bid": "0.002",
    "best_ask": "0.003",
    "last_trade_price": "0.002",
    "outcome_prices": "[\"0.0025\", \"0.9975\"]",
    "outcomes": "[\"Yes\", \"No\"]",
    "url": "https://polymarket.com/event/world-cup-winner",
    "matched_keywords": "2026;fifa;scotland;world cup",
    "notes": ""
  },
  {
    "discovered_at": "2026-06-11T07:31:51+00:00",
    "platform": "polymarket",
    "source": "gamma_events",
    "event_id": "30615",
    "event_slug": "world-cup-winner",
    "event_title": "World Cup Winner ",
    "market_id": "558948",
    "market_slug": "will-peru-win-the-2026-fifa-world-cup-981",
    "question": "Will Peru win the 2026 FIFA World Cup?",
    "event_type": "champion_or_outright",
    "active": true,
    "closed": true,
    "accepting_orders": "False",
    "end_date": "2026-07-20T00:00:00Z",
    "volume": 264589.508269,
    "volume_24hr": 100849187.11207904,
    "liquidity": 384055178.75338,
    "open_interest": 29394581.941327006,
    "best_bid": "",
    "best_ask": "0.001",
    "last_trade_price": "1",
    "outcome_prices": "[\"0\", \"1\"]",
    "outcomes": "[\"Yes\", \"No\"]",
    "url": "https://polymarket.com/event/world-cup-winner",
    "matched_keywords": "2026;fifa;world cup",
    "notes": ""
  },
  {
    "discovered_at": "2026-06-11T07:31:51+00:00",
    "platform": "polymarket",
    "source": "gamma_events",
    "event_id": "30615",
    "event_slug": "world-cup-winner",
    "event_title": "World Cup Winner ",
    "market_id": "558949",
    "market_slug": "will-japan-win-the-2026-fifa-world-cup-112",
    "question": "Will Japan win the 2026 FIFA World Cup?",
    "event_type": "champion_or_outright",
    "active": true,
    "closed": false,
    "accepting_orders": "True",
    "end_date": "2026-07-20T00:00:00Z",
    "volume": 40403722.44746603,
    "volume_24hr": 2369158.962403995,
    "liquidity": 1588900.85582,
    "open_interest": 29394581.941327006,
    "best_bid": "0.017",
    "best_ask": "0.018",
    "last_trade_price": "0.018",
    "outcome_prices": "[\"0.0175\", \"0.9825\"]",
    "outcomes": "[\"Yes\", \"No\"]",
    "url": "https://polymarket.com/event/world-cup-winner",
    "matched_keywords": "2026;fifa;japan;world cup",
    "notes": ""
  },
  {
    "discovered_at": "2026-06-11T07:31:51+00:00",
    "platform": "polymarket",
    "source": "gamma_events",
    "event_id": "30615",
    "event_slug": "world-cup-winner",
    "event_title": "World Cup Winner ",
    "market_id": "558951",
    "market_slug": "will-norway-win-the-2026-fifa-world-cup-893",
    "question": "Will Norway win the 2026 FIFA World Cup?",
    "event_type": "champion_or_outright",
    "active": true,
    "closed": false,
    "accepting_orders": "True",
    "end_date": "2026-07-20T00:00:00Z",
    "volume": 37170307.60229042,
    "volume_24hr": 1739323.468777001,
    "liquidity": 2993015.25729,
    "open_interest": 29394581.941327006,
    "best_bid": "0.024",
    "best_ask": "0.025",
    "last_trade_price": "0.024",
    "outcome_prices": "[\"0.0245\", \"0.9755\"]",
    "outcomes": "[\"Yes\", \"No\"]",
    "url": "https://polymarket.com/event/world-cup-winner",
    "matched_keywords": "2026;fifa;norway;world cup",
    "notes": ""
  },
  {
    "discovered_at": "2026-06-11T07:31:51+00:00",
    "platform": "polymarket",
    "source": "gamma_events",
    "event_id": "30615",
    "event_slug": "world-cup-winner",
    "event_title": "World Cup Winner ",
    "market_id": "558953",
    "market_slug": "will-any-other-team-win-the-2026-fifa-world-cup-541-319-294-845-754-317-243-911-472-778-811-233-235-839-426-488",
    "question": "Will Any Other Team win the 2026 FIFA World Cup?",
    "event_type": "champion_or_outright",
    "active": false,
    "closed": false,
    "accepting_orders": "True",
    "end_date": "2026-07-20T00:00:00Z",
    "volume": 0.0,
    "volume_24hr": 0.0,
    "liquidity": 0.0,
    "open_interest": 29394581.941327006,
    "best_bid": "0",
    "best_ask": "1",
    "last_trade_price": "0",
    "outcome_prices": "",
    "outcomes": "[\"Yes\", \"No\"]",
    "url": "https://polymarket.com/event/world-cup-winner",
    "matched_keywords": "2026;fifa;world cup",
    "notes": ""
  },
  {
    "discovered_at": "2026-06-11T07:31:51+00:00",
    "platform": "polymarket",
    "source": "gamma_events",
    "event_id": "30615",
    "event_slug": "world-cup-winner",
    "event_title": "World Cup Winner ",
    "market_id": "558986",
    "market_slug": "will-team-ag-win-the-2026-fifa-world-cup",
    "question": "Will Team AG win the 2026 FIFA World Cup?",
    "event_type": "champion_or_outright",
    "active": false,
    "closed": false,
    "accepting_orders": "True",
    "end_date": "2026-07-20T00:00:00Z",
    "volume": 0.0,
    "volume_24hr": 0.0,
    "liquidity": 0.0,
    "open_interest": 29394581.941327006,
    "best_bid": "0",
    "best_ask": "1",
    "last_trade_price": "0",
    "outcome_prices": "",
    "outcomes": "[\"Yes\", \"No\"]",
    "url": "https://polymarket.com/event/world-cup-winner",
    "matched_keywords": "2026;fifa;world cup",
    "notes": ""
  },
  {
    "discovered_at": "2026-06-11T07:31:51+00:00",
    "platform": "polymarket",
    "source": "gamma_events",
    "event_id": "30615",
    "event_slug": "world-cup-winner",
    "event_title": "World Cup Winner ",
    "market_id": "558954",
    "market_slug": "will-tunisia-win-the-2026-fifa-world-cup-165",
    "question": "Will Tunisia win the 2026 FIFA World Cup?",
    "event_type": "champion_or_outright",
    "active": true,
    "closed": false,
    "accepting_orders": "True",
    "end_date": "2026-07-20T00:00:00Z",
    "volume": 35506384.04368602,
    "volume_24hr": 187349.19,
    "liquidity": 14124047.39512,
    "open_interest": 29394581.941327006,
    "best_bid": "",
    "best_ask": "0.001",
    "last_trade_price": "0.001",
    "outcome_prices": "[\"0.0005\", \"0.9995\"]",
    "outcomes": "[\"Yes\", \"No\"]",
    "url": "https://polymarket.com/event/world-cup-winner",
    "matched_keywords": "2026;fifa;tunisia;world cup",
    "notes": ""
  },
  {
    "discovered_at": "2026-06-11T07:31:51+00:00",
    "platform": "polymarket",
    "source": "gamma_events",
    "event_id": "30615",
    "event_slug": "world-cup-winner",
    "event_title": "World Cup Winner ",
    "market_id": "558987",
    "market_slug": "will-team-ah-win-the-2026-fifa-world-cup",
    "question": "Will Team AH win the 2026 FIFA World Cup?",
    "event_type": "champion_or_outright",
    "active": false,
    "closed": false,
    "accepting_orders": "True",
    "end_date": "2026-07-20T00:00:00Z",
    "volume": 0.0,
    "volume_24hr": 0.0,
    "liquidity": 0.0,
    "open_interest": 29394581.941327006,
    "best_bid": "0",
    "best_ask": "1",
    "last_trade_price": "0",
    "outcome_prices": "",
    "outcomes": "[\"Yes\", \"No\"]",
    "url": "https://polymarket.com/event/world-cup-winner",
    "matched_keywords": "2026;fifa;world cup",
    "notes": ""
  },
  {
    "discovered_at": "2026-06-11T07:31:51+00:00",
    "platform": "polymarket",
    "source": "gamma_events",
    "event_id": "30615",
    "event_slug": "world-cup-winner",
    "event_title": "World Cup Winner ",
    "market_id": "558955",
    "market_slug": "will-ecuador-win-the-2026-fifa-world-cup-986",
    "question": "Will Ecuador win the 2026 FIFA World Cup?",
    "event_type": "champion_or_outright",
    "active": true,
    "closed": false,
    "accepting_orders": "True",
    "end_date": "2026-07-20T00:00:00Z",
    "volume": 44759943.916184634,
    "volume_24hr": 3087954.2071640044,
    "liquidity": 4042916.53142,
    "open_interest": 29394581.941327006,
    "best_bid": "0.008",
    "best_ask": "0.009",
    "last_trade_price": "0.008",
    "outcome_prices": "[\"0.0085\", \"0.9915\"]",
    "outcomes": "[\"Yes\", \"No\"]",
    "url": "https://polymarket.com/event/world-cup-winner",
    "matched_keywords": "2026;ecuador;fifa;world cup",
    "notes": ""
  },
  {
    "discovered_at": "2026-06-11T07:31:51+00:00",
    "platform": "polymarket",
    "source": "gamma_events",
    "event_id": "30615",
    "event_slug": "world-cup-winner",
    "event_title": "World Cup Winner ",
    "market_id": "558960",
    "market_slug": "will-uzbekistan-win-the-2026-fifa-world-cup-773",
    "question": "Will Uzbekistan win the 2026 FIFA World Cup?",
    "event_type": "champion_or_outright",
    "active": true,
    "closed": false,
    "accepting_orders": "True",
    "end_date": "2026-07-20T00:00:00Z",
    "volume": 59656927.18841757,
    "volume_24hr": 778980.0,
    "liquidity": 11668308.0328,
    "open_interest": 29394581.941327006,
    "best_bid": "",
    "best_ask": "0.001",
    "last_trade_price": "0.001",
    "outcome_prices": "[\"0.0005\", \"0.9995\"]",
    "outcomes": "[\"Yes\", \"No\"]",
    "url": "https://polymarket.com/event/world-cup-winner",
    "matched_keywords": "2026;fifa;uzbekistan;world cup",
    "notes": ""
  },
  {
    "discovered_at": "2026-06-11T07:31:51+00:00",
    "platform": "polymarket",
    "source": "gamma_events",
    "event_id": "30615",
    "event_slug": "world-cup-winner",
    "event_title": "World Cup Winner ",
    "market_id": "558963",
    "market_slug": "will-morocco-win-the-2026-fifa-world-cup-464",
    "question": "Will Morocco win the 2026 FIFA World Cup?",
    "event_type": "champion_or_outright",
    "active": true,
    "closed": false,
    "accepting_orders": "True",
    "end_date": "2026-07-20T00:00:00Z",
    "volume": 43892307.46384658,
    "volume_24hr": 2614395.594644001,
    "liquidity": 1259620.22716,
    "open_interest": 29394581.941327006,
    "best_bid": "0.015",
    "best_ask": "0.016",
    "last_trade_price": "0.015",
    "outcome_prices": "[\"0.0155\", \"0.9845\"]",
    "outcomes": "[\"Yes\", \"No\"]",
    "url": "https://polymarket.com/event/world-cup-winner",
    "matched_keywords": "2026;fifa;morocco;world cup",
    "notes": ""
  },
  {
    "discovered_at": "2026-06-11T07:31:51+00:00",
    "platform": "polymarket",
    "source": "gamma_events",
    "event_id": "30615",
    "event_slug": "world-cup-winner",
    "event_title": "World Cup Winner ",
    "market_id": "558979",
    "market_slug": "will-team-z-win-the-2026-fifa-world-cup-316",
    "question": "Will Panama win the 2026 FIFA World Cup?",
    "event_type": "champion_or_outright",
    "active": true,
    "closed": false,
    "accepting_orders": "True",
    "end_date": "2026-07-20T00:00:00Z",
    "volume": 19349382.76575688,
    "volume_24hr": 168064.0,
    "liquidity": 16959554.54728,
    "open_interest": 29394581.941327006,
    "best_bid": "",
    "best_ask": "0.001",
    "last_trade_price": "0.001",
    "outcome_prices": "[\"0.0005\", \"0.9995\"]",
    "outcomes": "[\"Yes\", \"No\"]",
    "url": "https://polymarket.com/event/world-cup-winner",
    "matched_keywords": "2026;fifa;panama;world cup",
    "notes": ""
  },
  {
    "discovered_at": "2026-06-11T07:31:51+00:00",
    "platform": "polymarket",
    "source": "gamma_events",
    "event_id": "30615",
    "event_slug": "world-cup-winner",
    "event_title": "World Cup Winner ",
    "market_id": "558982",
    "market_slug": "will-iraq-win-the-2026-fifa-world-cup",
    "question": "Will Iraq win the 2026 FIFA World Cup?",
    "event_type": "champion_or_outright",
    "active": true,
    "closed": false,
    "accepting_orders": "True",
    "end_date": "2026-07-20T00:00:00Z",
    "volume": 28864642.852710936,
    "volume_24hr": 245683.59,
    "liquidity": 17354906.49638,
    "open_interest": 29394581.941327006,
    "best_bid": "",
    "best_ask": "0.001",
    "last_trade_price": "0.001",
    "outcome_prices": "[\"0.0005\", \"0.9995\"]",
    "outcomes": "[\"Yes\", \"No\"]",
    "url": "https://polymarket.com/event/world-cup-winner",
    "matched_keywords": "2026;fifa;iraq;world cup",
    "notes": ""
  },
  {
    "discovered_at": "2026-06-11T07:31:51+00:00",
    "platform": "polymarket",
    "source": "gamma_events",
    "event_id": "30615",
    "event_slug": "world-cup-winner",
    "event_title": "World Cup Winner ",
    "market_id": "558964",
    "market_slug": "will-south-africa-win-the-2026-fifa-world-cup",
    "question": "Will South Africa win the 2026 FIFA World Cup?",
    "event_type": "champion_or_outright",
    "active": true,
    "closed": false,
    "accepting_orders": "True",
    "end_date": "2026-07-20T00:00:00Z",
    "volume": 38236335.207894266,
    "volume_24hr": 505555.0,
    "liquidity": 11225317.93698,
    "open_interest": 29394581.941327006,
    "best_bid": "",
    "best_ask": "0.001",
    "last_trade_price": "0.001",
    "outcome_prices": "[\"0.0005\", \"0.9995\"]",
    "outcomes": "[\"Yes\", \"No\"]",
    "url": "https://polymarket.com/event/world-cup-winner",
    "matched_keywords": "2026;fifa;south africa;world cup",
    "notes": ""
  },
  {
    "discovered_at": "2026-06-11T07:31:51+00:00",
    "platform": "polymarket",
    "source": "gamma_events",
    "event_id": "30615",
    "event_slug": "world-cup-winner",
    "event_title": "World Cup Winner ",
    "market_id": "558965",
    "market_slug": "will-senegal-win-the-2026-fifa-world-cup",
    "question": "Will Senegal win the 2026 FIFA World Cup?",
    "event_type": "champion_or_outright",
    "active": true,
    "closed": false,
    "accepting_orders": "True",
    "end_date": "2026-07-20T00:00:00Z",
    "volume": 38775566.092719376,
    "volume_24hr": 2451492.165963003,
    "liquidity": 5058128.23524,
    "open_interest": 29394581.941327006,
    "best_bid": "0.007",
    "best_ask": "0.008",
    "last_trade_price": "0.007",
    "outcome_prices": "[\"0.0075\", \"0.9925\"]",
    "outcomes": "[\"Yes\", \"No\"]",
    "url": "https://polymarket.com/event/world-cup-winner",
    "matched_keywords": "2026;fifa;senegal;world cup",
    "notes": ""
  },
  {
    "discovered_at": "2026-06-11T07:31:51+00:00",
    "platform": "polymarket",
    "source": "gamma_events",
    "event_id": "30615",
    "event_slug": "world-cup-winner",
    "event_title": "World Cup Winner ",
    "market_id": "558966",
    "market_slug": "will-ivory-coast-win-the-2026-fifa-world-cup",
    "question": "Will Ivory Coast win the 2026 FIFA World Cup?",
    "event_type": "champion_or_outright",
    "active": true,
    "closed": false,
    "accepting_orders": "True",
    "end_date": "2026-07-20T00:00:00Z",
    "volume": 52438180.3876243,
    "volume_24hr": 2324477.6885,
    "liquidity": 5730475.042,
    "open_interest": 29394581.941327006,
    "best_bid": "0.004",
    "best_ask": "0.005",
    "last_trade_price": "0.004",
    "outcome_prices": "[\"0.0045\", \"0.9955\"]",
    "outcomes": "[\"Yes\", \"No\"]",
    "url": "https://polymarket.com/event/world-cup-winner",
    "matched_keywords": "2026;fifa;ivory coast;world cup",
    "notes": ""
  },
  {
    "discovered_at": "2026-06-11T07:31:51+00:00",
    "platform": "polymarket",
    "source": "gamma_events",
    "event_id": "30615",
    "event_slug": "world-cup-winner",
    "event_title": "World Cup Winner ",
    "market_id": "558981",
    "market_slug": "will-congo-dr-win-the-2026-fifa-world-cup",
    "question": "Will Congo DR win the 2026 FIFA World Cup?",
    "event_type": "champion_or_outright",
    "active": true,
    "closed": false,
    "accepting_orders": "True",
    "end_date": "2026-07-20T00:00:00Z",
    "volume": 57620180.81140983,
    "volume_24hr": 1661221.8579999993,
    "liquidity": 9406223.82631,
    "open_interest": 29394581.941327006,
    "best_bid": "0.001",
    "best_ask": "0.002",
    "last_trade_price": "0.001",
    "outcome_prices": "[\"0.0015\", \"0.9985\"]",
    "outcomes": "[\"Yes\", \"No\"]",
    "url": "https://polymarket.com/event/world-cup-winner",
    "matched_keywords": "2026;congo;fifa;world cup",
    "notes": ""
  },
  {
    "discovered_at": "2026-06-11T07:31:51+00:00",
    "platform": "polymarket",
    "source": "gamma_events",
    "event_id": "30615",
    "event_slug": "world-cup-winner",
    "event_title": "World Cup Winner ",
    "market_id": "558970",
    "market_slug": "will-cape-verde-win-the-2026-fifa-world-cup",
    "question": "Will Cape Verde win the 2026 FIFA World Cup?",
    "event_type": "champion_or_outright",
    "active": true,
    "closed": false,
    "accepting_orders": "True",
    "end_date": "2026-07-20T00:00:00Z",
    "volume": 40166103.27716404,
    "volume_24hr": 160520.0,
    "liquidity": 16360233.05279,
    "open_interest": 29394581.941327006,
    "best_bid": "",
    "best_ask": "0.001",
    "last_trade_price": "0.001",
    "outcome_prices": "[\"0.0005\", \"0.9995\"]",
    "outcomes": "[\"Yes\", \"No\"]",
    "url": "https://polymarket.com/event/world-cup-winner",
    "matched_keywords": "2026;cape verde;fifa;world cup",
    "notes": ""
  },
  {
    "discovered_at": "2026-06-11T07:31:51+00:00",
    "platform": "polymarket",
    "source": "gamma_events",
    "event_id": "30615",
    "event_slug": "world-cup-winner",
    "event_title": "World Cup Winner ",
    "market_id": "558984",
    "market_slug": "will-czechia-win-the-2026-fifa-world-cup",
    "question": "Will Czechia win the 2026 FIFA World Cup?",
    "event_type": "champion_or_outright",
    "active": true,
    "closed": false,
    "accepting_orders": "True",
    "end_date": "2026-07-20T00:00:00Z",
    "volume": 30918074.53268298,
    "volume_24hr": 6173669.329487999,
    "liquidity": 9692144.87028,
    "open_interest": 29394581.941327006,
    "best_bid": "0.001",
    "best_ask": "0.002",
    "last_trade_price": "0.002",
    "outcome_prices": "[\"0.0015\", \"0.9985\"]",
    "outcomes": "[\"Yes\", \"No\"]",
    "url": "https://polymarket.com/event/world-cup-winner",
    "matched_keywords": "2026;czech;fifa;world cup",
    "notes": ""
  },
  {
    "discovered_at": "2026-06-11T07:31:51+00:00",
    "platform": "polymarket",
    "source": "gamma_events",
    "event_id": "30615",
    "event_slug": "world-cup-winner",
    "event_title": "World Cup Winner ",
    "market_id": "558971",
    "market_slug": "will-qatar-win-the-2026-fifa-world-cup",
    "question": "Will Qatar win the 2026 FIFA World Cup?",
    "event_type": "champion_or_outright",
    "active": true,
    "closed": false,
    "accepting_orders": "True",
    "end_date": "2026-07-20T00:00:00Z",
    "volume": 41894616.52833187,
    "volume_24hr": 448240.0,
    "liquidity": 16050135.97379,
    "open_interest": 29394581.941327006,
    "best_bid": "",
    "best_ask": "0.001",
    "last_trade_price": "0.001",
    "outcome_prices": "[\"0.0005\", \"0.9995\"]",
    "outcomes": "[\"Yes\", \"No\"]",
    "url": "https://polymarket.com/event/world-cup-winner",
    "matched_keywords": "2026;fifa;qatar;world cup",
    "notes": ""
  },
  {
    "discovered_at": "2026-06-11T07:31:51+00:00",
    "platform": "polymarket",
    "source": "gamma_events",
    "event_id": "30615",
    "event_slug": "world-cup-winner",
    "event_title": "World Cup Winner ",
    "market_id": "558946",
    "market_slug": "will-belgium-win-the-2026-fifa-world-cup-358",
    "question": "Will Belgium win the 2026 FIFA World Cup?",
    "event_type": "champion_or_outright",
    "active": true,
    "closed": false,
    "accepting_orders": "True",
    "end_date": "2026-07-20T00:00:00Z",
    "volume": 40096757.61534617,
    "volume_24hr": 2978067.979517006,
    "liquidity": 2724483.01301,
    "open_interest": 29394581.941327006,
    "best_bid": "0.021",
    "best_ask": "0.022",
    "last_trade_price": "0.021",
    "outcome_prices": "[\"0.0215\", \"0.9785\"]",
    "outcomes": "[\"Yes\", \"No\"]",
    "url": "https://polymarket.com/event/world-cup-winner",
    "matched_keywords": "2026;belgium;fifa;world cup",
    "notes": ""
  },
  {
    "discovered_at": "2026-06-11T07:31:51+00:00",
    "platform": "polymarket",
    "source": "gamma_events",
    "event_id": "30615",
    "event_slug": "world-cup-winner",
    "event_title": "World Cup Winner ",
    "market_id": "558958",
    "market_slug": "will-australia-win-the-2026-fifa-world-cup-816",
    "question": "Will Australia win the 2026 FIFA World Cup?",
    "event_type": "champion_or_outright",
    "active": true,
    "closed": false,
    "accepting_orders": "True",
    "end_date": "2026-07-20T00:00:00Z",
    "volume": 46087184.4865678,
    "volume_24hr": 1754578.622,
    "liquidity": 15771925.74656,
    "open_interest": 29394581.941327006,
    "best_bid": "0.001",
    "best_ask": "0.002",
    "last_trade_price": "0.002",
    "outcome_prices": "[\"0.0015\", \"0.9985\"]",
    "outcomes": "[\"Yes\", \"No\"]",
    "url": "https://polymarket.com/event/world-cup-winner",
    "matched_keywords": "2026;australia;fifa;world cup",
    "notes": ""
  },
  {
    "discovered_at": "2026-06-11T07:31:51+00:00",
    "platform": "polymarket",
    "source": "gamma_events",
    "event_id": "30615",
    "event_slug": "world-cup-winner",
    "event_title": "World Cup Winner ",
    "market_id": "558972",
    "market_slug": "will-saudi-arabia-win-the-2026-fifa-world-cup",
    "question": "Will Saudi Arabia win the 2026 FIFA World Cup?",
    "event_type": "champion_or_outright",
    "active": true,
    "closed": false,
    "accepting_orders": "True",
    "end_date": "2026-07-20T00:00:00Z",
    "volume": 47597314.91288372,
    "volume_24hr": 1549726.48,
    "liquidity": 11654503.01327,
    "open_interest": 29394581.941327006,
    "best_bid": "",
    "best_ask": "0.001",
    "last_trade_price": "0.001",
    "outcome_prices": "[\"0.0005\", \"0.9995\"]",
    "outcomes": "[\"Yes\", \"No\"]",
    "url": "https://polymarket.com/event/world-cup-winner",
    "matched_keywords": "2026;fifa;saudi;world cup",
    "notes": ""
  },
  {
    "discovered_at": "2026-06-11T07:31:51+00:00",
    "platform": "polymarket",
    "source": "gamma_events",
    "event_id": "30615",
    "event_slug": "world-cup-winner",
    "event_title": "World Cup Winner ",
    "market_id": "558991",
    "market_slug": "will-team-al-win-the-2026-fifa-world-cup",
    "question": "Will Team AL win the 2026 FIFA World Cup?",
    "event_type": "champion_or_outright",
    "active": false,
    "closed": false,
    "accepting_orders": "True",
    "end_date": "2026-07-20T00:00:00Z",
    "volume": 0.0,
    "volume_24hr": 0.0,
    "liquidity": 0.0,
    "open_interest": 29394581.941327006,
    "best_bid": "0",
    "best_ask": "1",
    "last_trade_price": "0",
    "outcome_prices": "",
    "outcomes": "[\"Yes\", \"No\"]",
    "url": "https://polymarket.com/event/world-cup-winner",
    "matched_keywords": "2026;fifa;world cup",
    "notes": ""
  },
  {
    "discovered_at": "2026-06-11T07:31:51+00:00",
    "platform": "polymarket",
    "source": "gamma_events",
    "event_id": "30615",
    "event_slug": "world-cup-winner",
    "event_title": "World Cup Winner ",
    "market_id": "558975",
    "market_slug": "will-austria-win-the-2026-fifa-world-cup",
    "question": "Will Austria win the 2026 FIFA World Cup?",
    "event_type": "champion_or_outright",
    "active": true,
    "closed": false,
    "accepting_orders": "True",
    "end_date": "2026-07-20T00:00:00Z",
    "volume": 43000665.535557404,
    "volume_24hr": 2381048.631749998,
    "liquidity": 4450577.42372,
    "open_interest": 29394581.941327006,
    "best_bid": "0.004",
    "best_ask": "0.005",
    "last_trade_price": "0.004",
    "outcome_prices": "[\"0.0045\", \"0.9955\"]",
    "outcomes": "[\"Yes\", \"No\"]",
    "url": "https://polymarket.com/event/world-cup-winner",
    "matched_keywords": "2026;austria;fifa;world cup",
    "notes": ""
  },
  {
    "discovered_at": "2026-06-11T07:31:51+00:00",
    "platform": "polymarket",
    "source": "gamma_events",
    "event_id": "30615",
    "event_slug": "world-cup-winner",
    "event_title": "World Cup Winner ",
    "market_id": "558976",
    "market_slug": "will-croatia-win-the-2026-fifa-world-cup",
    "question": "Will Croatia win the 2026 FIFA World Cup?",
    "event_type": "champion_or_outright",
    "active": true,
    "closed": false,
    "accepting_orders": "True",
    "end_date": "2026-07-20T00:00:00Z",
    "volume": 44966721.24368816,
    "volume_24hr": 2021335.1751869998,
    "liquidity": 2429955.5721,
    "open_interest": 29394581.941327006,
    "best_bid": "0.009",
    "best_ask": "0.01",
    "last_trade_price": "0.009",
    "outcome_prices": "[\"0.0095\", \"0.9905\"]",
    "outcomes": "[\"Yes\", \"No\"]",
    "url": "https://polymarket.com/event/world-cup-winner",
    "matched_keywords": "2026;croatia;fifa;world cup",
    "notes": ""
  },
  {
    "discovered_at": "2026-06-11T07:31:51+00:00",
    "platform": "polymarket",
    "source": "gamma_events",
    "event_id": "30615",
    "event_slug": "world-cup-winner",
    "event_title": "World Cup Winner ",
    "market_id": "558993",
    "market_slug": "will-team-an-win-the-2026-fifa-world-cup",
    "question": "Will Team AN win the 2026 FIFA World Cup?",
    "event_type": "champion_or_outright",
    "active": false,
    "closed": false,
    "accepting_orders": "True",
    "end_date": "2026-07-20T00:00:00Z",
    "volume": 0.0,
    "volume_24hr": 0.0,
    "liquidity": 0.0,
    "open_interest": 29394581.941327006,
    "best_bid": "0",
    "best_ask": "1",
    "last_trade_price": "0",
    "outcome_prices": "",
    "outcomes": "[\"Yes\", \"No\"]",
    "url": "https://polymarket.com/event/world-cup-winner",
    "matched_keywords": "2026;fifa;world cup",
    "notes": ""
  },
  {
    "discovered_at": "2026-06-11T07:31:51+00:00",
    "platform": "polymarket",
    "source": "gamma_events",
    "event_id": "30615",
    "event_slug": "world-cup-winner",
    "event_title": "World Cup Winner ",
    "market_id": "558968",
    "market_slug": "will-egypt-win-the-2026-fifa-world-cup",
    "question": "Will Egypt win the 2026 FIFA World Cup?",
    "event_type": "champion_or_outright",
    "active": true,
    "closed": false,
    "accepting_orders": "True",
    "end_date": "2026-07-20T00:00:00Z",
    "volume": 51081615.25087962,
    "volume_24hr": 1817063.4479810004,
    "liquidity": 6430252.88188,
    "open_interest": 29394581.941327006,
    "best_bid": "0.002",
    "best_ask": "0.003",
    "last_trade_price": "0.002",
    "outcome_prices": "[\"0.0025\", \"0.9975\"]",
    "outcomes": "[\"Yes\", \"No\"]",
    "url": "https://polymarket.com/event/world-cup-winner",
    "matched_keywords": "2026;egypt;fifa;world cup",
    "notes": ""
  },
  {
    "discovered_at": "2026-06-11T07:31:51+00:00",
    "platform": "polymarket",
    "source": "gamma_events",
    "event_id": "30615",
    "event_slug": "world-cup-winner",
    "event_title": "World Cup Winner ",
    "market_id": "558980",
    "market_slug": "will-sweden-win-the-2026-fifa-world-cup",
    "question": "Will Sweden win the 2026 FIFA World Cup?",
    "event_type": "champion_or_outright",
    "active": true,
    "closed": false,
    "accepting_orders": "True",
    "end_date": "2026-07-20T00:00:00Z",
    "volume": 29663107.723428164,
    "volume_24hr": 2105146.5379799996,
    "liquidity": 10802793.31514,
    "open_interest": 29394581.941327006,
    "best_bid": "0.003",
    "best_ask": "0.004",
    "last_trade_price": "0.003",
    "outcome_prices": "[\"0.0035\", \"0.9965\"]",
    "outcomes": "[\"Yes\", \"No\"]",
    "url": "https://polymarket.com/event/world-cup-winner",
    "matched_keywords": "2026;fifa;sweden;world cup",
    "notes": ""
  },
  {
    "discovered_at": "2026-06-11T07:31:51+00:00",
    "platform": "polymarket",
    "source": "gamma_events",
    "event_id": "30615",
    "event_slug": "world-cup-winner",
    "event_title": "World Cup Winner ",
    "market_id": "558989",
    "market_slug": "will-team-aj-win-the-2026-fifa-world-cup",
    "question": "Will Team AJ win the 2026 FIFA World Cup?",
    "event_type": "champion_or_outright",
    "active": false,
    "closed": false,
    "accepting_orders": "True",
    "end_date": "2026-07-20T00:00:00Z",
    "volume": 0.0,
    "volume_24hr": 0.0,
    "liquidity": 0.0,
    "open_interest": 29394581.941327006,
    "best_bid": "0",
    "best_ask": "1",
    "last_trade_price": "0",
    "outcome_prices": "",
    "outcomes": "[\"Yes\", \"No\"]",
    "url": "https://polymarket.com/event/world-cup-winner",
    "matched_keywords": "2026;fifa;world cup",
    "notes": ""
  },
  {
    "discovered_at": "2026-06-11T07:31:51+00:00",
    "platform": "polymarket",
    "source": "gamma_events",
    "event_id": "30615",
    "event_slug": "world-cup-winner",
    "event_title": "World Cup Winner ",
    "market_id": "558990",
    "market_slug": "will-team-ak-win-the-2026-fifa-world-cup",
    "question": "Will Team AK win the 2026 FIFA World Cup?",
    "event_type": "champion_or_outright",
    "active": false,
    "closed": false,
    "accepting_orders": "True",
    "end_date": "2026-07-20T00:00:00Z",
    "volume": 0.0,
    "volume_24hr": 0.0,
    "liquidity": 0.0,
    "open_interest": 29394581.941327006,
    "best_bid": "0",
    "best_ask": "1",
    "last_trade_price": "0",
    "outcome_prices": "",
    "outcomes": "[\"Yes\", \"No\"]",
    "url": "https://polymarket.com/event/world-cup-winner",
    "matched_keywords": "2026;fifa;world cup",
    "notes": ""
  },
  {
    "discovered_at": "2026-06-11T07:31:51+00:00",
    "platform": "polymarket",
    "source": "gamma_events",
    "event_id": "30615",
    "event_slug": "world-cup-winner",
    "event_title": "World Cup Winner ",
    "market_id": "558994",
    "market_slug": "will-team-ao-win-the-2026-fifa-world-cup",
    "question": "Will Team AO win the 2026 FIFA World Cup?",
    "event_type": "champion_or_outright",
    "active": false,
    "closed": false,
    "accepting_orders": "True",
    "end_date": "2026-07-20T00:00:00Z",
    "volume": 0.0,
    "volume_24hr": 0.0,
    "liquidity": 0.0,
    "open_interest": 29394581.941327006,
    "best_bid": "0",
    "best_ask": "1",
    "last_trade_price": "0",
    "outcome_prices": "",
    "outcomes": "[\"Yes\", \"No\"]",
    "url": "https://polymarket.com/event/world-cup-winner",
    "matched_keywords": "2026;fifa;world cup",
    "notes": ""
  },
  {
    "discovered_at": "2026-06-11T07:31:51+00:00",
    "platform": "polymarket",
    "source": "gamma_events",
    "event_id": "38368",
    "event_slug": "will-any-2026-fifa-world-cup-game-scheduled-in-the-us-be-relocated-abroad",
    "event_title": "Will any World Cup game scheduled in the U.S. be relocated abroad?",
    "market_id": "578157",
    "market_slug": "will-any-2026-fifa-world-cup-game-scheduled-in-the-us-be-relocated-abroad",
    "question": "Will any World Cup game scheduled in the U.S. be relocated abroad?",
    "event_type": "special_event",
    "active": true,
    "closed": false,
    "accepting_orders": "True",
    "end_date": "2026-06-10T00:00:00Z",
    "volume": 22023.936846000004,
    "volume_24hr": 24.237141,
    "liquidity": 1315.46233,
    "open_interest": 8440.166817,
    "best_bid": "",
    "best_ask": "0.019",
    "last_trade_price": "0.041",
    "outcome_prices": "[\"0.0095\", \"0.9905\"]",
    "outcomes": "[\"Yes\", \"No\"]",
    "url": "https://polymarket.com/event/will-any-2026-fifa-world-cup-game-scheduled-in-the-us-be-relocated-abroad",
    "matched_keywords": "2026;canada;fifa;mexico;united states;usa;world cup",
    "notes": ""
  }
]